<?xml version="1.0" encoding="UTF-8"?>
<blueprint xmlns="http://www.osgi.org/xmlns/blueprint/v1.0.0">

  <bean id="roundRobinStrategy"
        class="io.subutai.core.strategy.impl.RoundRobinStrategy">
  </bean>

  <bean id="defaultStrategy"
        class="io.subutai.core.strategy.impl.DefaultContainerPlacementStrategy">
  </bean>

  <bean id="bestServerStrategy"
        class="io.subutai.core.strategy.impl.BestServerStrategy">
  </bean>

  <bean id="strategyManager" scope="singleton"
        class="io.subutai.core.strategy.impl.StrategyManagerImpl"
        destroy-method="destroy">
  </bean>

  <reference-list id="placementStrategies"
                  interface="io.subutai.core.strategy.api.ContainerPlacementStrategy"
                  availability="optional">
    <reference-listener ref="strategyManager"
                        bind-method="registerStrategy" unbind-method="unregisterStrategy" />
  </reference-list>

  <service ref="strategyManager" interface="io.subutai.core.strategy.api.StrategyManager" />
  <service ref="roundRobinStrategy" interface="io.subutai.core.strategy.api.ContainerPlacementStrategy" />
  <service ref="defaultStrategy" interface="io.subutai.core.strategy.api.ContainerPlacementStrategy" />
  <service ref="bestServerStrategy" interface="io.subutai.core.strategy.api.ContainerPlacementStrategy" />

</blueprint>
